blockchainetl
ethereumetl
matic_script_tester
tests
