Metadata-Version: 2.1
Name: matic-etl
Version: 0.0.2
Summary: Tools for exporting Matic blockchain data to CSV or JSON
Home-page: https://github.com/contxts-io/matic-etl
Author: Jetson Lim
Author-email: jetson@contxts.io
License: UNKNOWN
Keywords: ethereum
Platform: UNKNOWN
Classifier: Development Status :: 5 - Production/Stable
Classifier: Intended Audience :: Developers
Classifier: License :: OSI Approved :: MIT License
Classifier: Programming Language :: Python :: 3
Classifier: Programming Language :: Python :: 3.5
Classifier: Programming Language :: Python :: 3.6
Classifier: Programming Language :: Python :: 3.7
Classifier: Programming Language :: Python :: 3.8
Requires-Python: >=3.5.3,<4
Provides-Extra: streaming
Provides-Extra: dev
